pscrape/__init__.py
pscrape/scraper.py
pscrape-0.0.3.dist-info/LICENSE.txt
pscrape-0.0.3.dist-info/METADATA
pscrape-0.0.3.dist-info/WHEEL
pscrape-0.0.3.dist-info/entry_points.txt
pscrape-0.0.3.dist-info/top_level.txt
pscrape-0.0.3.dist-info/RECORD
