Metadata-Version: 2.1
Name: pscrape
Version: 0.0.3
Summary: Quickly generate a list of free and working proxies
Home-page: https://github.com/lbirchler/pscrape
Author: lbirchler
Classifier: Programming Language :: Python :: 3
Classifier: License :: OSI Approved :: MIT License
Requires-Python: >=3.8
License-File: LICENSE.txt
Requires-Dist: requests
Requires-Dist: beautifulsoup4
